maniera/__init__.py
maniera/__main__.py
maniera/calculator.py
maniera-1.0.2.dist-info/LICENSE
maniera-1.0.2.dist-info/METADATA
maniera-1.0.2.dist-info/WHEEL
maniera-1.0.2.dist-info/entry_points.txt
maniera-1.0.2.dist-info/top_level.txt
maniera-1.0.2.dist-info/RECORD
