Metadata-Version: 2.1
Name: maniera
Version: 1.0.2
Summary: An osu! Mania PP and star rating calculator.
Home-page: https://github.com/NiceAesth/maniera
Author: Nice Aesthetics
Author-email: nice@aesth.dev
License: GPLv3+
Keywords: osu! osu
Platform: UNKNOWN
Classifier: Intended Audience :: Developers
Classifier: License :: OSI Approved :: GNU General Public License v3 or later (GPLv3+)
Classifier: Programming Language :: Python :: 3
Classifier: Programming Language :: Python :: 3.7
